aiossechat/__init__.py
aiossechat/client.py
aiossechat/datatypes.py
aiossechat-0.0.5.dist-info/METADATA
aiossechat-0.0.5.dist-info/WHEEL
aiossechat-0.0.5.dist-info/top_level.txt
aiossechat-0.0.5.dist-info/RECORD
