Metadata-Version: 2.1
Name: aiossechat
Version: 0.0.5
Summary: A simple sse implementation with aiohttp, which is specifically designed for chatting with LLM.
Home-page: https://github.com/92MING/aiossechat
Author: 92MING
Author-email: yashin.sd123@yahoo.com.hk
Classifier: Programming Language :: Python :: 3
Classifier: License :: OSI Approved :: MIT License
Classifier: Operating System :: OS Independent
